celldex/__init__.py
celldex/fetch_reference.py
celldex/list_references.py
celldex/list_versions.py
celldex/save_reference.py
celldex/search_references.py
celldex/upload_reference.py
celldex/utils.py
celldex-0.3.0.dist-info/LICENSE.txt
celldex-0.3.0.dist-info/METADATA
celldex-0.3.0.dist-info/WHEEL
celldex-0.3.0.dist-info/top_level.txt
celldex-0.3.0.dist-info/RECORD
