Metadata-Version: 2.2
Name: celldex
Version: 0.3.0
Summary: Index of Reference Cell Type Datasets
Home-page: https://github.com/SingleR-inc/celldex
Author: Jayaram Kancherla
Author-email: jayaram.kancherla@gmail.com
License: MIT
Project-URL: Documentation, https://github.com/SingleR-inc/celldex
Platform: any
Classifier: Development Status :: 4 - Beta
Classifier: Programming Language :: Python
Requires-Python: >=3.9
License-File: LICENSE.txt
Requires-Dist: importlib-metadata; python_version < "3.8"
Requires-Dist: dolomite_base
Requires-Dist: dolomite_matrix
Requires-Dist: dolomite_sce>=0.1.2
Requires-Dist: gypsum_client>=0.1.3
Requires-Dist: delayedarray>=0.5.1
Requires-Dist: summarizedexperiment
Requires-Dist: singlecellexperiment
Requires-Dist: biocframe
Provides-Extra: testing
Requires-Dist: setuptools; extra == "testing"
Requires-Dist: pytest; extra == "testing"
Requires-Dist: pytest-cov; extra == "testing"
